{"rendered": {"message": {"raw": "Merged in cbillington/lyse/feature3 (pull request #12)\n\nCopy plot to clipboard\n\nApproved-by: Philip Starkey <philip.starkey@monash.edu>", "markup": "markdown", "html": "<p>Merged in <a href=\"#!/cbillington/lyse\" rel=\"nofollow\" class=\"ap-connect-link\">cbillington/lyse</a>/feature3 (pull request #12)</p>\n<p>Copy plot to clipboard</p>\n<p>Approved-by: Philip Starkey <a href=\"mailto:philip.starkey@monash.edu\">&#112;&#104;&#105;&#108;&#105;&#112;&#46;&#115;&#116;&#97;&#114;&#107;&#101;&#121;&#64;&#109;&#111;&#110;&#97;&#115;&#104;&#46;&#101;&#100;&#117;</a></p>", "type": "rendered"}}, "hash": "8b07419dca65d6c9762d59b6a550dd2262b00dd9", "repository": {"links": {"self": {"href": "data/repositories/pstarkey/lyse.json"}, "html": {"href": "#!/pstarkey/lyse"}, "avatar": {"href": "data/bytebucket.org/ravatar/{e5413385-6166-4d2c-9b39-d34598d7fb72}ts=python"}}, "type": "repository", "name": "lyse", "full_name": "pstarkey/lyse", "uuid": "{e5413385-6166-4d2c-9b39-d34598d7fb72}"}, "links": {"self": {"href": "data/repositories/pstarkey/lyse/commit/8b07419dca65d6c9762d59b6a550dd2262b00dd9.json"}, "comments": {"href": "data/repositories/pstarkey/lyse/commit/8b07419dca65d6c9762d59b6a550dd2262b00dd9/comments_page=1.json"}, "html": {"href": "#!/pstarkey/lyse/commits/8b07419dca65d6c9762d59b6a550dd2262b00dd9"}, "diff": {"href": "https://api.bitbucket.org/2.0/repositories/pstarkey/lyse/diff/8b07419dca65d6c9762d59b6a550dd2262b00dd9"}, "approve": {"href": "https://api.bitbucket.org/2.0/repositories/pstarkey/lyse/commit/8b07419dca65d6c9762d59b6a550dd2262b00dd9/approve"}, "statuses": {"href": "data/repositories/pstarkey/lyse/commit/8b07419dca65d6c9762d59b6a550dd2262b00dd9/statuses_page=1.json"}}, "author": {"raw": "Philip Starkey <philip.starkey@monash.edu>", "type": "author", "user": {"display_name": "Phil Starkey", "uuid": "{bf2034f3-ffd1-49fb-9bf4-e900788cfbff}", "links": {"self": {"href": "https://api.bitbucket.org/2.0/users/%7Bbf2034f3-ffd1-49fb-9bf4-e900788cfbff%7D"}, "html": {"href": "https://bitbucket.org/%7Bbf2034f3-ffd1-49fb-9bf4-e900788cfbff%7D/"}, "avatar": {"href": "data/secure.gravatar.com/avatar/a5d16233c76364a4acbdc83e9ee02d96d=httpsavatar-management--avatars.us-west-2.prod.public.atl-paas.netinitialsPS-3.png"}}, "nickname": "Philip Starkey", "type": "user", "account_id": "5e2d536c52522c0e6fe716ed"}}, "summary": {"raw": "Merged in cbillington/lyse/feature3 (pull request #12)\n\nCopy plot to clipboard\n\nApproved-by: Philip Starkey <philip.starkey@monash.edu>", "markup": "markdown", "html": "<p>Merged in <a href=\"#!/cbillington/lyse\" rel=\"nofollow\" class=\"ap-connect-link\">cbillington/lyse</a>/feature3 (pull request #12)</p>\n<p>Copy plot to clipboard</p>\n<p>Approved-by: Philip Starkey <a href=\"mailto:philip.starkey@monash.edu\">&#112;&#104;&#105;&#108;&#105;&#112;&#46;&#115;&#116;&#97;&#114;&#107;&#101;&#121;&#64;&#109;&#111;&#110;&#97;&#115;&#104;&#46;&#101;&#100;&#117;</a></p>", "type": "rendered"}, "participants": [], "parents": [{"hash": "c4908e5d0a94634ee9f53b85d44b645b46d12a2e", "type": "commit", "links": {"self": {"href": "data/repositories/pstarkey/lyse/commit/c4908e5d0a94634ee9f53b85d44b645b46d12a2e.json"}, "html": {"href": "#!/pstarkey/lyse/commits/c4908e5d0a94634ee9f53b85d44b645b46d12a2e"}}}, {"hash": "0bb629e431be9bd4b0a4bea90bce3f2a58947f6c", "type": "commit", "links": {"self": {"href": "data/repositories/pstarkey/lyse/commit/0bb629e431be9bd4b0a4bea90bce3f2a58947f6c.json"}, "html": {"href": "#!/pstarkey/lyse/commits/0bb629e431be9bd4b0a4bea90bce3f2a58947f6c"}}}], "date": "2017-04-26T05:15:14+00:00", "message": "Merged in cbillington/lyse/feature3 (pull request #12)\n\nCopy plot to clipboard\n\nApproved-by: Philip Starkey <philip.starkey@monash.edu>", "type": "commit", "git_hash": "82ffc051fa22c6681d2c6ec12db4a4079ed5fc75", "tags": null, "branches": "default"}