{"rendered": {"message": {"raw": "Merged in cbillington/labscript_utils/feature2 (pull request #14)\n\nMake analog output widgets not steal focus on scrolling\n\nApproved-by: Shaun Johnstone <shaun.johnstone@monash.edu>\nApproved-by: Philip Starkey <philip.starkey@monash.edu>", "markup": "markdown", "html": "<p>Merged in <a href=\"#!/cbillington/labscript_utils\" rel=\"nofollow\" class=\"ap-connect-link\">cbillington/labscript_utils</a>/feature2 (pull request #14)</p>\n<p>Make analog output widgets not steal focus on scrolling</p>\n<p>Approved-by: Shaun Johnstone <a href=\"mailto:shaun.johnstone@monash.edu\">&#115;&#104;&#97;&#117;&#110;&#46;&#106;&#111;&#104;&#110;&#115;&#116;&#111;&#110;&#101;&#64;&#109;&#111;&#110;&#97;&#115;&#104;&#46;&#101;&#100;&#117;</a><br />\nApproved-by: Philip Starkey <a href=\"mailto:philip.starkey@monash.edu\">&#112;&#104;&#105;&#108;&#105;&#112;&#46;&#115;&#116;&#97;&#114;&#107;&#101;&#121;&#64;&#109;&#111;&#110;&#97;&#115;&#104;&#46;&#101;&#100;&#117;</a></p>", "type": "rendered"}}, "hash": "f5c421e37ab43df295beff00bf1a910ba80ea976", "repository": {"links": {"self": {"href": "data/repositories/synqs/labscript_utils.json"}, "html": {"href": "#!/synqs/labscript_utils"}, "avatar": {"href": "data/bytebucket.org/ravatar/{cdc4a353-bea9-4d28-9a14-3ef107e5d030}ts=python"}}, "type": "repository", "name": "labscript_utils", "full_name": "synqs/labscript_utils", "uuid": "{cdc4a353-bea9-4d28-9a14-3ef107e5d030}"}, "links": {"self": {"href": "data/repositories/synqs/labscript_utils/commit/f5c421e37ab43df295beff00bf1a910ba80ea976.json"}, "comments": {"href": "data/repositories/synqs/labscript_utils/commit/f5c421e37ab43df295beff00bf1a910ba80ea976/comments_page=1.json"}, "html": {"href": "#!/synqs/labscript_utils/commits/f5c421e37ab43df295beff00bf1a910ba80ea976"}, "diff": {"href": "https://api.bitbucket.org/2.0/repositories/synqs/labscript_utils/diff/f5c421e37ab43df295beff00bf1a910ba80ea976"}, "approve": {"href": "https://api.bitbucket.org/2.0/repositories/synqs/labscript_utils/commit/f5c421e37ab43df295beff00bf1a910ba80ea976/approve"}, "statuses": {"href": "data/repositories/synqs/labscript_utils/commit/f5c421e37ab43df295beff00bf1a910ba80ea976/statuses_page=1.json"}}, "author": {"raw": "Philip Starkey <philip.starkey@monash.edu>", "type": "author", "user": {"display_name": "Philip Starkey", "uuid": "{48af65db-e5fc-459c-a7eb-52eb1f9a5690}", "links": {"self": {"href": "https://api.bitbucket.org/2.0/users/%7B48af65db-e5fc-459c-a7eb-52eb1f9a5690%7D"}, "html": {"href": "https://bitbucket.org/%7B48af65db-e5fc-459c-a7eb-52eb1f9a5690%7D/"}, "avatar": {"href": "data/secure.gravatar.com/avatar/dc318537facc47ebe1ae98a7aabacecfd=httpsavatar-management--avatars.us-west-2.prod.public.atl-paas.netinitialsPS-0.png"}}, "nickname": "pstarkey", "type": "user", "account_id": "557058:52a111e4-40da-4441-9143-417f95f2db97"}}, "summary": {"raw": "Merged in cbillington/labscript_utils/feature2 (pull request #14)\n\nMake analog output widgets not steal focus on scrolling\n\nApproved-by: Shaun Johnstone <shaun.johnstone@monash.edu>\nApproved-by: Philip Starkey <philip.starkey@monash.edu>", "markup": "markdown", "html": "<p>Merged in <a href=\"#!/cbillington/labscript_utils\" rel=\"nofollow\" class=\"ap-connect-link\">cbillington/labscript_utils</a>/feature2 (pull request #14)</p>\n<p>Make analog output widgets not steal focus on scrolling</p>\n<p>Approved-by: Shaun Johnstone <a href=\"mailto:shaun.johnstone@monash.edu\">&#115;&#104;&#97;&#117;&#110;&#46;&#106;&#111;&#104;&#110;&#115;&#116;&#111;&#110;&#101;&#64;&#109;&#111;&#110;&#97;&#115;&#104;&#46;&#101;&#100;&#117;</a><br />\nApproved-by: Philip Starkey <a href=\"mailto:philip.starkey@monash.edu\">&#112;&#104;&#105;&#108;&#105;&#112;&#46;&#115;&#116;&#97;&#114;&#107;&#101;&#121;&#64;&#109;&#111;&#110;&#97;&#115;&#104;&#46;&#101;&#100;&#117;</a></p>", "type": "rendered"}, "participants": [], "parents": [{"hash": "15ae72adb07232ba894562f5ade6c1c8e74121c8", "type": "commit", "links": {"self": {"href": "data/repositories/synqs/labscript_utils/commit/15ae72adb07232ba894562f5ade6c1c8e74121c8.json"}, "html": {"href": "#!/synqs/labscript_utils/commits/15ae72adb07232ba894562f5ade6c1c8e74121c8"}}}, {"hash": "814986b7174fbf4e6cc97757c919ee9ec6e1dcd8", "type": "commit", "links": {"self": {"href": "data/repositories/synqs/labscript_utils/commit/814986b7174fbf4e6cc97757c919ee9ec6e1dcd8.json"}, "html": {"href": "#!/synqs/labscript_utils/commits/814986b7174fbf4e6cc97757c919ee9ec6e1dcd8"}}}], "date": "2017-06-27T06:54:27+00:00", "message": "Merged in cbillington/labscript_utils/feature2 (pull request #14)\n\nMake analog output widgets not steal focus on scrolling\n\nApproved-by: Shaun Johnstone <shaun.johnstone@monash.edu>\nApproved-by: Philip Starkey <philip.starkey@monash.edu>", "type": "commit", "git_hash": "661025c576a1014f7ea27acb2300c32e23cd54c8", "tags": null, "branches": "default"}