{"pagelen": 100, "values": [{"changes": {"state": {"new": "wontfix", "old": "new"}}, "links": {"self": {"href": "data/repositories/labscript_suite/blacs/issues/25/changes/39039882.json"}, "html": {"href": "#!/labscript_suite/blacs/issues/25#comment-39039882"}}, "issue": {"links": {"self": {"href": "data/repositories/labscript_suite/blacs/issues/25.json"}}, "type": "issue", "id": 25, "repository": {"links": {"self": {"href": "data/repositories/labscript_suite/blacs.json"}, "html": {"href": "#!/labscript_suite/blacs"}, "avatar": {"href": "data/bytebucket.org/ravatar/{50ed1eb9-8c1b-4afe-a8b8-8e0a33b39a05}ts=249915"}}, "type": "repository", "name": "BLACS", "full_name": "labscript_suite/blacs", "uuid": "{50ed1eb9-8c1b-4afe-a8b8-8e0a33b39a05}"}, "title": "Error when starting BLACS from console"}, "created_on": "2017-08-11T15:14:24.020021+00:00", "user": {"display_name": "Chris Billington", "uuid": "{e363c5a9-5075-4656-afb5-88bd6a6dceeb}", "links": {"self": {"href": "https://api.bitbucket.org/2.0/users/%7Be363c5a9-5075-4656-afb5-88bd6a6dceeb%7D"}, "html": {"href": "https://bitbucket.org/%7Be363c5a9-5075-4656-afb5-88bd6a6dceeb%7D/"}, "avatar": {"href": "data/secure.gravatar.com/avatar/9238baf7300c41c0e7294db922899e6ad=httpsavatar-management--avatars.us-west-2.prod.public.atl-paas.netinitialsCB-1.png"}}, "nickname": "cbillington", "type": "user", "account_id": "557058:cbf1bc43-1dc2-477b-9e25-1a8f40fd7ee3"}, "message": {"raw": null, "markup": "markdown", "html": "", "type": "rendered"}, "type": "issue_change", "id": 39039882}], "page": 1, "size": 1}