{"pagelen": 50, "values": [{"comment": {"links": {"self": {"href": "data/repositories/labscript_suite/runviewer/pullrequests/20/comments/59392389.json"}, "html": {"href": "#!/labscript_suite/runviewer/pull-requests/20/_/diff#comment-59392389"}}, "parent": {"id": 59392087, "links": {"self": {"href": "data/repositories/labscript_suite/runviewer/pullrequests/20/comments/59392087.json"}, "html": {"href": "#!/labscript_suite/runviewer/pull-requests/20/_/diff#comment-59392087"}}}, "deleted": false, "pullrequest": {"type": "pullrequest", "id": 20, "links": {"self": {"href": "data/repositories/labscript_suite/runviewer/pullrequests/20.json"}, "html": {"href": "#!/labscript_suite/runviewer/pull-requests/20"}}, "title": "Minor Python 3 fix"}, "content": {"raw": "I'll scan all of the python 3 changes for decode/encode statements later or maybe tomorrow. \n\nI tried finding information in the h5py documentation but that didn't really help much. So checking and not assuming a type is  probably the way to go for now.", "markup": "markdown", "html": "<p>I'll scan all of the python 3 changes for decode/encode statements later or maybe tomorrow. </p>\n<p>I tried finding information in the h5py documentation but that didn't really help much. So checking and not assuming a type is  probably the way to go for now.</p>", "type": "rendered"}, "created_on": "2018-03-20T21:47:11.749484+00:00", "user": {"display_name": "Jan Werkmann", "uuid": "{44c4905c-2b90-4045-a5f1-652b8e228626}", "links": {"self": {"href": "https://api.bitbucket.org/2.0/users/%7B44c4905c-2b90-4045-a5f1-652b8e228626%7D"}, "html": {"href": "https://bitbucket.org/%7B44c4905c-2b90-4045-a5f1-652b8e228626%7D/"}, "avatar": {"href": "https://avatar-management--avatars.us-west-2.prod.public.atl-paas.net/557058:a70cc9cf-684e-4849-a61a-9ade4d7218b5/07e5095a-4741-4dc0-a462-9c7d455f961d/128"}}, "nickname": "PhyNerd", "type": "user", "account_id": "557058:a70cc9cf-684e-4849-a61a-9ade4d7218b5"}, "updated_on": "2018-03-20T21:47:11.793216+00:00", "type": "pullrequest_comment", "id": 59392389}, "pull_request": {"type": "pullrequest", "id": 20, "links": {"self": {"href": "data/repositories/labscript_suite/runviewer/pullrequests/20.json"}, "html": {"href": "#!/labscript_suite/runviewer/pull-requests/20"}}, "title": "Minor Python 3 fix"}}, {"update": {"description": "Today I was doing some python 3 testing and run files compiled with python3 resulted in a unicode master pseudoclock name \\(Python 2 ones did not\\). I'm not quite sure when attributes are unicode and when they are byte strings so I added a check before trying to decode to prevent a exception.", "title": "Minor Python 3 fix", "destination": {"commit": {"hash": "ee9f51c06c8f", "type": "commit", "links": {"self": {"href": "data/repositories/labscript_suite/runviewer/commit/ee9f51c06c8f.json"}, "html": {"href": "#!/labscript_suite/runviewer/commits/ee9f51c06c8f"}}}, "repository": {"links": {"self": {"href": "data/repositories/labscript_suite/runviewer.json"}, "html": {"href": "#!/labscript_suite/runviewer"}, "avatar": {"href": "data/bytebucket.org/ravatar/{71215673-ad3e-425c-ae04-84cc6c2ca7da}ts=445022"}}, "type": "repository", "name": "runviewer", "full_name": "labscript_suite/runviewer", "uuid": "{71215673-ad3e-425c-ae04-84cc6c2ca7da}"}, "branch": {"name": "default"}}, "reason": "", "source": {"commit": {"hash": "59134bad193e", "type": "commit", "links": {"self": {"href": "https://api.bitbucket.org/2.0/repositories/PhyNerd/runviewer/commit/59134bad193e"}, "html": {"href": "#!/PhyNerd/runviewer/commits/59134bad193e"}}}, "repository": {"links": {"self": {"href": "https://api.bitbucket.org/2.0/repositories/PhyNerd/runviewer"}, "html": {"href": "#!/PhyNerd/runviewer"}, "avatar": {"href": "data/bytebucket.org/ravatar/{8e4d590c-fc3c-46d3-99aa-340c3f9e0df6}ts=python"}}, "type": "repository", "name": "runviewer", "full_name": "PhyNerd/runviewer", "uuid": "{8e4d590c-fc3c-46d3-99aa-340c3f9e0df6}"}, "branch": {"name": "minor-python3-fix"}}, "state": "MERGED", "author": {"display_name": "Chris Billington", "uuid": "{e363c5a9-5075-4656-afb5-88bd6a6dceeb}", "links": {"self": {"href": "https://api.bitbucket.org/2.0/users/%7Be363c5a9-5075-4656-afb5-88bd6a6dceeb%7D"}, "html": {"href": "https://bitbucket.org/%7Be363c5a9-5075-4656-afb5-88bd6a6dceeb%7D/"}, "avatar": {"href": "data/secure.gravatar.com/avatar/9238baf7300c41c0e7294db922899e6ad=httpsavatar-management--avatars.us-west-2.prod.public.atl-paas.netinitialsCB-1.png"}}, "nickname": "cbillington", "type": "user", "account_id": "557058:cbf1bc43-1dc2-477b-9e25-1a8f40fd7ee3"}, "date": "2018-03-20T21:44:22.109780+00:00"}, "pull_request": {"type": "pullrequest", "id": 20, "links": {"self": {"href": "data/repositories/labscript_suite/runviewer/pullrequests/20.json"}, "html": {"href": "#!/labscript_suite/runviewer/pull-requests/20"}}, "title": "Minor Python 3 fix"}}, {"approval": {"date": "2018-03-20T21:43:18.932616+00:00", "pullrequest": {"type": "pullrequest", "id": 20, "links": {"self": {"href": "data/repositories/labscript_suite/runviewer/pullrequests/20.json"}, "html": {"href": "#!/labscript_suite/runviewer/pull-requests/20"}}, "title": "Minor Python 3 fix"}, "user": {"display_name": "Chris Billington", "uuid": "{e363c5a9-5075-4656-afb5-88bd6a6dceeb}", "links": {"self": {"href": "https://api.bitbucket.org/2.0/users/%7Be363c5a9-5075-4656-afb5-88bd6a6dceeb%7D"}, "html": {"href": "https://bitbucket.org/%7Be363c5a9-5075-4656-afb5-88bd6a6dceeb%7D/"}, "avatar": {"href": "data/secure.gravatar.com/avatar/9238baf7300c41c0e7294db922899e6ad=httpsavatar-management--avatars.us-west-2.prod.public.atl-paas.netinitialsCB-1.png"}}, "nickname": "cbillington", "type": "user", "account_id": "557058:cbf1bc43-1dc2-477b-9e25-1a8f40fd7ee3"}}, "pull_request": {"type": "pullrequest", "id": 20, "links": {"self": {"href": "data/repositories/labscript_suite/runviewer/pullrequests/20.json"}, "html": {"href": "#!/labscript_suite/runviewer/pull-requests/20"}}, "title": "Minor Python 3 fix"}}, {"comment": {"links": {"self": {"href": "data/repositories/labscript_suite/runviewer/pullrequests/20/comments/59392087.json"}, "html": {"href": "#!/labscript_suite/runviewer/pull-requests/20/_/diff#comment-59392087"}}, "deleted": false, "pullrequest": {"type": "pullrequest", "id": 20, "links": {"self": {"href": "data/repositories/labscript_suite/runviewer/pullrequests/20.json"}, "html": {"href": "#!/labscript_suite/runviewer/pull-requests/20"}}, "title": "Minor Python 3 fix"}, "content": {"raw": "As a general rule for porting labscript stuff to Python 3, code reading any string should try to accept it whether it is a bytestring or a unicode string (decoding with utf8 if it finds a bytestring), so this is the right change IMHO.", "markup": "markdown", "html": "<p>As a general rule for porting labscript stuff to Python 3, code reading any string should try to accept it whether it is a bytestring or a unicode string (decoding with utf8 if it finds a bytestring), so this is the right change IMHO.</p>", "type": "rendered"}, "created_on": "2018-03-20T21:42:59.782938+00:00", "user": {"display_name": "Chris Billington", "uuid": "{e363c5a9-5075-4656-afb5-88bd6a6dceeb}", "links": {"self": {"href": "https://api.bitbucket.org/2.0/users/%7Be363c5a9-5075-4656-afb5-88bd6a6dceeb%7D"}, "html": {"href": "https://bitbucket.org/%7Be363c5a9-5075-4656-afb5-88bd6a6dceeb%7D/"}, "avatar": {"href": "data/secure.gravatar.com/avatar/9238baf7300c41c0e7294db922899e6ad=httpsavatar-management--avatars.us-west-2.prod.public.atl-paas.netinitialsCB-1.png"}}, "nickname": "cbillington", "type": "user", "account_id": "557058:cbf1bc43-1dc2-477b-9e25-1a8f40fd7ee3"}, "updated_on": "2018-03-20T21:43:08.882962+00:00", "type": "pullrequest_comment", "id": 59392087}, "pull_request": {"type": "pullrequest", "id": 20, "links": {"self": {"href": "data/repositories/labscript_suite/runviewer/pullrequests/20.json"}, "html": {"href": "#!/labscript_suite/runviewer/pull-requests/20"}}, "title": "Minor Python 3 fix"}}, {"update": {"description": "Today I was doing some python 3 testing and run files compiled with python3 resulted in a unicode master pseudoclock name \\(Python 2 ones did not\\). I'm not quite sure when attributes are unicode and when they are byte strings so I added a check before trying to decode to prevent a exception.", "title": "Minor Python 3 fix", "destination": {"commit": {"hash": "ee9f51c06c8f", "type": "commit", "links": {"self": {"href": "data/repositories/labscript_suite/runviewer/commit/ee9f51c06c8f.json"}, "html": {"href": "#!/labscript_suite/runviewer/commits/ee9f51c06c8f"}}}, "repository": {"links": {"self": {"href": "data/repositories/labscript_suite/runviewer.json"}, "html": {"href": "#!/labscript_suite/runviewer"}, "avatar": {"href": "data/bytebucket.org/ravatar/{71215673-ad3e-425c-ae04-84cc6c2ca7da}ts=445022"}}, "type": "repository", "name": "runviewer", "full_name": "labscript_suite/runviewer", "uuid": "{71215673-ad3e-425c-ae04-84cc6c2ca7da}"}, "branch": {"name": "default"}}, "reason": "", "source": {"commit": {"hash": "59134bad193e", "type": "commit", "links": {"self": {"href": "https://api.bitbucket.org/2.0/repositories/PhyNerd/runviewer/commit/59134bad193e"}, "html": {"href": "#!/PhyNerd/runviewer/commits/59134bad193e"}}}, "repository": {"links": {"self": {"href": "https://api.bitbucket.org/2.0/repositories/PhyNerd/runviewer"}, "html": {"href": "#!/PhyNerd/runviewer"}, "avatar": {"href": "data/bytebucket.org/ravatar/{8e4d590c-fc3c-46d3-99aa-340c3f9e0df6}ts=python"}}, "type": "repository", "name": "runviewer", "full_name": "PhyNerd/runviewer", "uuid": "{8e4d590c-fc3c-46d3-99aa-340c3f9e0df6}"}, "branch": {"name": "minor-python3-fix"}}, "state": "OPEN", "author": {"display_name": "Jan Werkmann", "uuid": "{44c4905c-2b90-4045-a5f1-652b8e228626}", "links": {"self": {"href": "https://api.bitbucket.org/2.0/users/%7B44c4905c-2b90-4045-a5f1-652b8e228626%7D"}, "html": {"href": "https://bitbucket.org/%7B44c4905c-2b90-4045-a5f1-652b8e228626%7D/"}, "avatar": {"href": "https://avatar-management--avatars.us-west-2.prod.public.atl-paas.net/557058:a70cc9cf-684e-4849-a61a-9ade4d7218b5/07e5095a-4741-4dc0-a462-9c7d455f961d/128"}}, "nickname": "PhyNerd", "type": "user", "account_id": "557058:a70cc9cf-684e-4849-a61a-9ade4d7218b5"}, "date": "2018-03-20T21:17:45.794969+00:00"}, "pull_request": {"type": "pullrequest", "id": 20, "links": {"self": {"href": "data/repositories/labscript_suite/runviewer/pullrequests/20.json"}, "html": {"href": "#!/labscript_suite/runviewer/pull-requests/20"}}, "title": "Minor Python 3 fix"}}, {"update": {"description": "Today I was doing some python 3 testing and run files compiled with python3 resulted in a unicode master pseudoclock name \\(Python 2 ones did not\\). I'm not quite sure when attributes are unicode and when they are byte strings so I added a check before trying to decode to prevent a exception.", "title": "Minor Python 3 fix", "destination": {"commit": {"hash": "ee9f51c06c8f", "type": "commit", "links": {"self": {"href": "data/repositories/labscript_suite/runviewer/commit/ee9f51c06c8f.json"}, "html": {"href": "#!/labscript_suite/runviewer/commits/ee9f51c06c8f"}}}, "repository": {"links": {"self": {"href": "data/repositories/labscript_suite/runviewer.json"}, "html": {"href": "#!/labscript_suite/runviewer"}, "avatar": {"href": "data/bytebucket.org/ravatar/{71215673-ad3e-425c-ae04-84cc6c2ca7da}ts=445022"}}, "type": "repository", "name": "runviewer", "full_name": "labscript_suite/runviewer", "uuid": "{71215673-ad3e-425c-ae04-84cc6c2ca7da}"}, "branch": {"name": "default"}}, "reason": "", "source": {"commit": {"hash": "59134bad193e", "type": "commit", "links": {"self": {"href": "https://api.bitbucket.org/2.0/repositories/PhyNerd/runviewer/commit/59134bad193e"}, "html": {"href": "#!/PhyNerd/runviewer/commits/59134bad193e"}}}, "repository": {"links": {"self": {"href": "https://api.bitbucket.org/2.0/repositories/PhyNerd/runviewer"}, "html": {"href": "#!/PhyNerd/runviewer"}, "avatar": {"href": "data/bytebucket.org/ravatar/{8e4d590c-fc3c-46d3-99aa-340c3f9e0df6}ts=python"}}, "type": "repository", "name": "runviewer", "full_name": "PhyNerd/runviewer", "uuid": "{8e4d590c-fc3c-46d3-99aa-340c3f9e0df6}"}, "branch": {"name": "minor-python3-fix"}}, "state": "OPEN", "author": {"display_name": "Jan Werkmann", "uuid": "{44c4905c-2b90-4045-a5f1-652b8e228626}", "links": {"self": {"href": "https://api.bitbucket.org/2.0/users/%7B44c4905c-2b90-4045-a5f1-652b8e228626%7D"}, "html": {"href": "https://bitbucket.org/%7B44c4905c-2b90-4045-a5f1-652b8e228626%7D/"}, "avatar": {"href": "https://avatar-management--avatars.us-west-2.prod.public.atl-paas.net/557058:a70cc9cf-684e-4849-a61a-9ade4d7218b5/07e5095a-4741-4dc0-a462-9c7d455f961d/128"}}, "nickname": "PhyNerd", "type": "user", "account_id": "557058:a70cc9cf-684e-4849-a61a-9ade4d7218b5"}, "date": "2018-03-20T21:17:45.743528+00:00"}, "pull_request": {"type": "pullrequest", "id": 20, "links": {"self": {"href": "data/repositories/labscript_suite/runviewer/pullrequests/20.json"}, "html": {"href": "#!/labscript_suite/runviewer/pull-requests/20"}}, "title": "Minor Python 3 fix"}}]}