{"links": {"self": {"href": "data/repositories/labscript_suite/labscript_devices/pullrequests/35/comments/70771475.json"}, "html": {"href": "#!/labscript_suite/labscript_devices/pull-requests/35/_/diff#comment-70771475"}}, "deleted": false, "pullrequest": {"type": "pullrequest", "id": 35, "links": {"self": {"href": "data/repositories/labscript_suite/labscript_devices/pullrequests/35.json"}, "html": {"href": "#!/labscript_suite/labscript_devices/pull-requests/35"}}, "title": "Python3 Camera"}, "content": {"raw": "I think this should be merged next.   \nThe zmq part is well tested in our lab.   \nThe python socket implementation probably still needs all its strings converted to byte strings, but I\u2019m not sure about this.", "markup": "markdown", "html": "<p>I think this should be merged next. <br />\nThe zmq part is well tested in our lab. <br />\nThe python socket implementation probably still needs all its strings converted to byte strings, but I\u2019m not sure about this.</p>", "type": "rendered"}, "created_on": "2018-07-23T19:56:22.720719+00:00", "user": {"display_name": "Jan Werkmann", "uuid": "{44c4905c-2b90-4045-a5f1-652b8e228626}", "links": {"self": {"href": "https://api.bitbucket.org/2.0/users/%7B44c4905c-2b90-4045-a5f1-652b8e228626%7D"}, "html": {"href": "https://bitbucket.org/%7B44c4905c-2b90-4045-a5f1-652b8e228626%7D/"}, "avatar": {"href": "https://avatar-management--avatars.us-west-2.prod.public.atl-paas.net/557058:a70cc9cf-684e-4849-a61a-9ade4d7218b5/07e5095a-4741-4dc0-a462-9c7d455f961d/128"}}, "nickname": "PhyNerd", "type": "user", "account_id": "557058:a70cc9cf-684e-4849-a61a-9ade4d7218b5"}, "updated_on": "2018-07-23T19:56:22.788925+00:00", "type": "pullrequest_comment", "id": 70771475}