{"rendered": {"message": {"raw": "Merged in cbillington/blacs/bugfix2 (pull request #6)\n\nReduce average shot turnaround time by 0.625 seconds\n\nApproved-by: Philip Starkey <philip.starkey@monash.edu>", "markup": "markdown", "html": "<p>Merged in <a href=\"#!/cbillington/blacs\" rel=\"nofollow\" class=\"ap-connect-link\">cbillington/blacs</a>/bugfix2 (pull request #6)</p>\n<p>Reduce average shot turnaround time by 0.625 seconds</p>\n<p>Approved-by: Philip Starkey <a href=\"mailto:philip.starkey@monash.edu\">&#112;&#104;&#105;&#108;&#105;&#112;&#46;&#115;&#116;&#97;&#114;&#107;&#101;&#121;&#64;&#109;&#111;&#110;&#97;&#115;&#104;&#46;&#101;&#100;&#117;</a></p>", "type": "rendered"}}, "hash": "d075c69632b20d376d05915020d26ae4b5b1572b", "repository": {"links": {"self": {"href": "data/repositories/cavitylab/blacs.json"}, "html": {"href": "#!/cavitylab/blacs"}, "avatar": {"href": "data/bytebucket.org/ravatar/{95ce113a-2d94-42de-b9fb-c31ba362c5f1}ts=python"}}, "type": "repository", "name": "BLACS", "full_name": "cavitylab/blacs", "uuid": "{95ce113a-2d94-42de-b9fb-c31ba362c5f1}"}, "links": {"self": {"href": "data/repositories/cavitylab/blacs/commit/d075c69632b20d376d05915020d26ae4b5b1572b.json"}, "comments": {"href": "data/repositories/cavitylab/blacs/commit/d075c69632b20d376d05915020d26ae4b5b1572b/comments_page=1.json"}, "html": {"href": "#!/cavitylab/blacs/commits/d075c69632b20d376d05915020d26ae4b5b1572b"}, "diff": {"href": "https://api.bitbucket.org/2.0/repositories/cavitylab/blacs/diff/d075c69632b20d376d05915020d26ae4b5b1572b"}, "approve": {"href": "https://api.bitbucket.org/2.0/repositories/cavitylab/blacs/commit/d075c69632b20d376d05915020d26ae4b5b1572b/approve"}, "statuses": {"href": "data/repositories/cavitylab/blacs/commit/d075c69632b20d376d05915020d26ae4b5b1572b/statuses_page=1.json"}}, "author": {"raw": "Philip Starkey <philip.starkey@monash.edu>", "type": "author", "user": {"display_name": "Phil Starkey", "uuid": "{bf2034f3-ffd1-49fb-9bf4-e900788cfbff}", "links": {"self": {"href": "https://api.bitbucket.org/2.0/users/%7Bbf2034f3-ffd1-49fb-9bf4-e900788cfbff%7D"}, "html": {"href": "https://bitbucket.org/%7Bbf2034f3-ffd1-49fb-9bf4-e900788cfbff%7D/"}, "avatar": {"href": "data/secure.gravatar.com/avatar/a5d16233c76364a4acbdc83e9ee02d96d=httpsavatar-management--avatars.us-west-2.prod.public.atl-paas.netinitialsPS-3.png"}}, "nickname": "Philip Starkey", "type": "user", "account_id": "5e2d536c52522c0e6fe716ed"}}, "summary": {"raw": "Merged in cbillington/blacs/bugfix2 (pull request #6)\n\nReduce average shot turnaround time by 0.625 seconds\n\nApproved-by: Philip Starkey <philip.starkey@monash.edu>", "markup": "markdown", "html": "<p>Merged in <a href=\"#!/cbillington/blacs\" rel=\"nofollow\" class=\"ap-connect-link\">cbillington/blacs</a>/bugfix2 (pull request #6)</p>\n<p>Reduce average shot turnaround time by 0.625 seconds</p>\n<p>Approved-by: Philip Starkey <a href=\"mailto:philip.starkey@monash.edu\">&#112;&#104;&#105;&#108;&#105;&#112;&#46;&#115;&#116;&#97;&#114;&#107;&#101;&#121;&#64;&#109;&#111;&#110;&#97;&#115;&#104;&#46;&#101;&#100;&#117;</a></p>", "type": "rendered"}, "participants": [], "parents": [{"hash": "96d4e099f3c1fbc274ff8747c72a5a7b5f989629", "type": "commit", "links": {"self": {"href": "data/repositories/cavitylab/blacs/commit/96d4e099f3c1fbc274ff8747c72a5a7b5f989629.json"}, "html": {"href": "#!/cavitylab/blacs/commits/96d4e099f3c1fbc274ff8747c72a5a7b5f989629"}}}, {"hash": "eb622809f2937e43910e147d646cf952360f64f4", "type": "commit", "links": {"self": {"href": "data/repositories/cavitylab/blacs/commit/eb622809f2937e43910e147d646cf952360f64f4.json"}, "html": {"href": "#!/cavitylab/blacs/commits/eb622809f2937e43910e147d646cf952360f64f4"}}}], "date": "2017-06-07T23:04:34+00:00", "message": "Merged in cbillington/blacs/bugfix2 (pull request #6)\n\nReduce average shot turnaround time by 0.625 seconds\n\nApproved-by: Philip Starkey <philip.starkey@monash.edu>", "type": "commit", "git_hash": "f227a720aa819f96f03655542e63c0e43bd66dbf", "tags": null, "branches": "default"}